{
  "csv": "/Users/souba636/Documents/Research/Projects/vinnova_paper_2/Federated_IDS/attack_data/blackhole_var15_dec/17_features_timeseries_60_sec.csv",
  "domain": "blackhole_var15_dec",
  "file": "17_features_timeseries_60_sec.csv",
  "n_train": 436,
  "n_features": 14,
  "n_sparse": 6,
  "sparse_features": [
    "disr",
    "diss",
    "diar",
    "disr.1",
    "diss.1",
    "diar.1"
  ],
  "ks_mean": 0.2041,
  "ks_pass": 4,
  "ks_total": 14,
  "ks_per_feature": [
    {
      "feature": "dior.1",
      "ks_stat": 0.3523,
      "p_value": 0.0,
      "pass": false
    },
    {
      "feature": "rank",
      "ks_stat": 0.3428,
      "p_value": 0.0,
      "pass": false
    },
    {
      "feature": "tots.1",
      "ks_stat": 0.3159,
      "p_value": 0.0,
      "pass": false
    },
    {
      "feature": "dios.1",
      "ks_stat": 0.3088,
      "p_value": 0.0,
      "pass": false
    },
    {
      "feature": "dios",
      "ks_stat": 0.2846,
      "p_value": 0.0,
      "pass": false
    },
    {
      "feature": "diar",
      "ks_stat": 0.2793,
      "p_value": 0.0,
      "pass": false
    },
    {
      "feature": "dior",
      "ks_stat": 0.2596,
      "p_value": 0.0,
      "pass": false
    },
    {
      "feature": "tots",
      "ks_stat": 0.2498,
      "p_value": 0.0,
      "pass": false
    },
    {
      "feature": "diar.1",
      "ks_stat": 0.2414,
      "p_value": 0.0,
      "pass": false
    },
    {
      "feature": "rank.1",
      "ks_stat": 0.2146,
      "p_value": 0.0,
      "pass": false
    },
    {
      "feature": "disr",
      "ks_stat": 0.003,
      "p_value": 1.0,
      "pass": true
    },
    {
      "feature": "diss.1",
      "ks_stat": 0.003,
      "p_value": 1.0,
      "pass": true
    },
    {
      "feature": "diss",
      "ks_stat": 0.001,
      "p_value": 1.0,
      "pass": true
    },
    {
      "feature": "disr.1",
      "ks_stat": 0.001,
      "p_value": 1.0,
      "pass": true
    }
  ],
  "tstr_f1": 0.4104,
  "trts_f1": 0.3333,
  "base_f1": 0.0,
  "gap": 0.0771
}